medical_data/__init__.py
medical_data/dataset.py
medical_data/indexing.py
medical_data/modality.py
medical_data/moving_avg.py
medical_data/single_class.py
medical_data/transforms.py
medical_data/utils.py
tests/data/test_modality.py
medical_data-0.2.0.dist-info/LICENSE
medical_data-0.2.0.dist-info/METADATA
medical_data-0.2.0.dist-info/WHEEL
medical_data-0.2.0.dist-info/top_level.txt
medical_data-0.2.0.dist-info/zip-safe
medical_data-0.2.0.dist-info/RECORD
