Metadata-Version: 2.1
Name: medical-data
Version: 0.2.0
Summary: Helpful data utilities for deep learning in medical image analysis/medical image computing
Author: Justus Schock
Author-email: justus.schock@posteo.de
Maintainer-email: Justus Schock <justus.schock@posteo.de>
License: Apache License
Project-URL: Homepage, https://github.com/justusschock/medical-data
Project-URL: Repository, https://github.com/justusschock/medical-data
Project-URL: Bug Reports, https://github.com/justusschock/medical-data/issues
Keywords: deep learning,machine learning,pytorch,medical,healthcare,AI
Classifier: Programming Language :: Python :: 3
Requires-Python: >=3.8
License-File: LICENSE
Requires-Dist: torch (<3.0,>=1.9)
Requires-Dist: psutil (<5.9.2)
Requires-Dist: torchio (<0.18.79,>0.18.56)
Requires-Dist: lightning (<3.0,>=2.0)
Requires-Dist: lightning-utilities (<0.9,>=0.5)
Requires-Dist: monai (<1.1.1,>=0.7)
Requires-Dist: loguru (==0.7.0)
Requires-Dist: psutil (<5.9.6)
Requires-Dist: torchio (<0.18.92,>0.18.56)
Requires-Dist: pytorch-lightning (>=1.5)
Requires-Dist: loguru (>=0.6.0)
Requires-Dist: pydicom
Requires-Dist: jsonargparse
Provides-Extra: test
Requires-Dist: pytest ; extra == 'test'
Requires-Dist: coverage ; extra == 'test'
